{
  "metricName": "automationRate",
  "generatedAt": "2026-01-19T10:15:00Z",
  "interval": "1d",
  "data": [
    {
      "date": "2026-01-13",
      "rate": 0.34
    },
    {
      "date": "2026-01-14",
      "rate": 0.31
    },
    {
      "date": "2026-01-15",
      "rate": 0.36
    },
    {
      "date": "2026-01-16",
      "rate": 0.38
    },
    {
      "date": "2026-01-17",
      "rate": 0.33
    },
    {
      "date": "2026-01-18",
      "rate": 0.35
    },
    {
      "date": "2026-01-19",
      "rate": 0.37
    }
  ]
}
